ksvmlib/__init__.py
ksvmlib/ksvm.py
ksvmlib/plot.py
ksvmlib/metrics/__init__.py
ksvmlib/metrics/accuracy.py
ksvmlib/metrics/svmbic.py
ksvmlib-0.1.1.dist-info/LICENSE.txt
ksvmlib-0.1.1.dist-info/METADATA
ksvmlib-0.1.1.dist-info/WHEEL
ksvmlib-0.1.1.dist-info/top_level.txt
ksvmlib-0.1.1.dist-info/RECORD
